[{"id":"1214012002","districtId":"121401","name":"Hilisangowola"},{"id":"1214012005","districtId":"121401","name":"Hiliotalua"},{"id":"1214012006","districtId":"121401","name":"Koendrafo"},{"id":"1214012008","districtId":"121401","name":"Lawa-lawa Luo"},{"id":"1214012016","districtId":"121401","name":"Tuhemberua"},{"id":"1214012017","districtId":"121401","name":"Tesikhori"},{"id":"1214012021","districtId":"121401","name":"Tumari"},{"id":"1214012023","districtId":"121401","name":"Ewo"},{"id":"1214012024","districtId":"121401","name":"Ko'olotano"},{"id":"1214012026","districtId":"121401","name":"Botohilindruria"},{"id":"1214012027","districtId":"121401","name":"Caritas Sogawunasi"},{"id":"1214012028","districtId":"121401","name":"Orudua Lawa-lawa Luo"},{"id":"1214012029","districtId":"121401","name":"Hilifaondrato"}]