[{"id":"1306082001","districtId":"130608","name":"Koto Tinggi"},{"id":"1306082002","districtId":"130608","name":"Tabek Panjang"},{"id":"1306082004","districtId":"130608","name":"Simarasok"},{"id":"1306082005","districtId":"130608","name":"Padang Tarok"},{"id":"1306082006","districtId":"130608","name":"Salo"},{"id":"1306082007","districtId":"130608","name":"Koto Baru"},{"id":"1306082008","districtId":"130608","name":"Sungai Cubadak"},{"id":"1306082009","districtId":"130608","name":"Koto Gadang"}]