[{"id":"1402051005","districtId":"140205","name":"Peranap"},{"id":"1402051008","districtId":"140205","name":"Batu Rijal Hilir"},{"id":"1402052003","districtId":"140205","name":"Semelinang Tebing"},{"id":"1402052004","districtId":"140205","name":"Gumanti"},{"id":"1402052007","districtId":"140205","name":"Batu Rijal Hulu"},{"id":"1402052009","districtId":"140205","name":"Semelinang Darat"},{"id":"1402052010","districtId":"140205","name":"Pauh Ranap"},{"id":"1402052012","districtId":"140205","name":"Serai Wangi"},{"id":"1402052013","districtId":"140205","name":"Pandan Wangi"},{"id":"1402052017","districtId":"140205","name":"Katipo Pura"},{"id":"1402052019","districtId":"140205","name":"Batu Rijal Barat"},{"id":"1402052020","districtId":"140205","name":"Setako Raya"}]