[{"id":"1608152001","districtId":"160815","name":"Karang Melati"},{"id":"1608152002","districtId":"160815","name":"Karang Menjangan"},{"id":"1608152003","districtId":"160815","name":"Karang Anyar"},{"id":"1608152004","districtId":"160815","name":"Tulung Harapan"},{"id":"1608152005","districtId":"160815","name":"Kota Tanah"},{"id":"1608152006","districtId":"160815","name":"Nirwana"},{"id":"1608152007","districtId":"160815","name":"Burnai Mulya"},{"id":"1608152008","districtId":"160815","name":"Kota Mulya"},{"id":"1608152009","districtId":"160815","name":"Bungin Jaya"},{"id":"1608152010","districtId":"160815","name":"Burnai Jaya"},{"id":"1608152011","districtId":"160815","name":"Mulia Jaya"},{"id":"1608152012","districtId":"160815","name":"Melati Jaya"},{"id":"1608152013","districtId":"160815","name":"Karang Mulya"},{"id":"1608152014","districtId":"160815","name":"Wanasari"},{"id":"1608152015","districtId":"160815","name":"Harapan Jaya"},{"id":"1608152016","districtId":"160815","name":"Melati Agung"},{"id":"1608152017","districtId":"160815","name":"Wana Makmur"},{"id":"1608152018","districtId":"160815","name":"Bawang Tikar"},{"id":"1608152019","districtId":"160815","name":"Karya Bakti"}]