[{"id":"1709082001","districtId":"170908","name":"Komering"},{"id":"1709082002","districtId":"170908","name":"Bajak Tiga"},{"id":"1709082003","districtId":"170908","name":"Rajak Besi"},{"id":"1709082004","districtId":"170908","name":"Punjung"},{"id":"1709082005","districtId":"170908","name":"Susup"},{"id":"1709082006","districtId":"170908","name":"Arga Indah II"},{"id":"1709082007","districtId":"170908","name":"Curup"},{"id":"1709082008","districtId":"170908","name":"Karang Panggung"},{"id":"1709082009","districtId":"170908","name":"Lubuk Pendam"},{"id":"1709082010","districtId":"170908","name":"Lubuk Puar"},{"id":"1709082011","districtId":"170908","name":"Durian Lebar"},{"id":"1709082012","districtId":"170908","name":"Pagar Agung"},{"id":"1709082013","districtId":"170908","name":"Pungguk Jaya"},{"id":"1709082014","districtId":"170908","name":"Taba Gemantung"},{"id":"1709082015","districtId":"170908","name":"Pagar Besi"}]