[{"id":"1802202001","districtId":"180220","name":"Nyukang Harjo"},{"id":"1802202002","districtId":"180220","name":"Lingga Pura"},{"id":"1802202003","districtId":"180220","name":"Sido Harjo"},{"id":"1802202004","districtId":"180220","name":"Taman Sari"},{"id":"1802202005","districtId":"180220","name":"Karang Anyar"},{"id":"1802202006","districtId":"180220","name":"Negeri Katon"},{"id":"1802202007","districtId":"180220","name":"Gedung Harta"},{"id":"1802202008","districtId":"180220","name":"Tanjung Ratu"},{"id":"1802202009","districtId":"180220","name":"Negeri Agung"},{"id":"1802202010","districtId":"180220","name":"Gilih Karang Jati"},{"id":"1802202011","districtId":"180220","name":"Marga Jaya"},{"id":"1802202012","districtId":"180220","name":"Gedung Aji"},{"id":"1802202013","districtId":"180220","name":"Negeri Jaya"},{"id":"1802202014","districtId":"180220","name":"Mekar Harjo"}]