[{"id":"1812072001","districtId":"181207","name":"Kibang Budi Jaya"},{"id":"1812072002","districtId":"181207","name":"Lesung Bhakti Jaya"},{"id":"1812072003","districtId":"181207","name":"Mekar Sari Jaya"},{"id":"1812072004","districtId":"181207","name":"Pagar Jaya"},{"id":"1812072005","districtId":"181207","name":"Gunung Sari"},{"id":"1812072006","districtId":"181207","name":"Sumber Rejo"},{"id":"1812072007","districtId":"181207","name":"Kibang Yekti Jaya"},{"id":"1812072008","districtId":"181207","name":"Kibang Tri Jaya"},{"id":"1812072009","districtId":"181207","name":"Gilang Tunggal Makarta"},{"id":"1812072010","districtId":"181207","name":"Kibang Mulya Jaya"}]