[{"id":"3201352001","districtId":"320135","name":"Cisarua"},{"id":"3201352002","districtId":"320135","name":"Kiarasari"},{"id":"3201352003","districtId":"320135","name":"Sukajaya"},{"id":"3201352004","districtId":"320135","name":"Sipayung"},{"id":"3201352005","districtId":"320135","name":"Cileuksa"},{"id":"3201352006","districtId":"320135","name":"Kiarapandak"},{"id":"3201352007","districtId":"320135","name":"Harkatjaya"},{"id":"3201352008","districtId":"320135","name":"Sukamulih"},{"id":"3201352009","districtId":"320135","name":"Pasir Madang"},{"id":"3201352010","districtId":"320135","name":"Urug"},{"id":"3201352011","districtId":"320135","name":"Jayaraharja"}]