[{"id":"3201302001","districtId":"320130","name":"Sukadamai"},{"id":"3201302002","districtId":"320130","name":"Ciherang"},{"id":"3201302003","districtId":"320130","name":"Sinarsari"},{"id":"3201302004","districtId":"320130","name":"Sukawening"},{"id":"3201302005","districtId":"320130","name":"Petir"},{"id":"3201302006","districtId":"320130","name":"Purwasari"},{"id":"3201302007","districtId":"320130","name":"Cikarawang"},{"id":"3201302008","districtId":"320130","name":"Babakan"},{"id":"3201302009","districtId":"320130","name":"Dramaga"},{"id":"3201302010","districtId":"320130","name":"Neglasari"}]