[{"id":"3215302001","districtId":"321530","name":"Kertamukti"},{"id":"3215302002","districtId":"321530","name":"Rawasari"},{"id":"3215302003","districtId":"321530","name":"Pusakajaya Selatan"},{"id":"3215302004","districtId":"321530","name":"Cikande"},{"id":"3215302005","districtId":"321530","name":"Kosambibatu"},{"id":"3215302006","districtId":"321530","name":"Pusakajaya Utara"},{"id":"3215302007","districtId":"321530","name":"Sukaratu"},{"id":"3215302008","districtId":"321530","name":"Ciptamargi"},{"id":"3215302009","districtId":"321530","name":"Mekarpohaci"},{"id":"3215302010","districtId":"321530","name":"Tanjungsari"}]