[{"id":"3307101010","districtId":"330710","name":"Wonoroto"},{"id":"3307102001","districtId":"330710","name":"Bumiroso"},{"id":"3307102002","districtId":"330710","name":"Gondang"},{"id":"3307102003","districtId":"330710","name":"Limbangan"},{"id":"3307102004","districtId":"330710","name":"Kuripan"},{"id":"3307102005","districtId":"330710","name":"Banyukembar"},{"id":"3307102006","districtId":"330710","name":"Gumawangkidul"},{"id":"3307102007","districtId":"330710","name":"Wonosroyo"},{"id":"3307102008","districtId":"330710","name":"Watumalang"},{"id":"3307102009","districtId":"330710","name":"Pasuruhan"},{"id":"3307102011","districtId":"330710","name":"Lumajang"},{"id":"3307102012","districtId":"330710","name":"Binangun"},{"id":"3307102013","districtId":"330710","name":"Wonokampir"},{"id":"3307102014","districtId":"330710","name":"Krinjing"},{"id":"3307102015","districtId":"330710","name":"Mutisari"},{"id":"3307102016","districtId":"330710","name":"Kalidesel"}]