[{"id":"3327012001","districtId":"332701","name":"Plakaran"},{"id":"3327012002","districtId":"332701","name":"Mandiraja"},{"id":"3327012003","districtId":"332701","name":"Walangsanga"},{"id":"3327012004","districtId":"332701","name":"Sima"},{"id":"3327012005","districtId":"332701","name":"Moga"},{"id":"3327012006","districtId":"332701","name":"Banyumudal"},{"id":"3327012007","districtId":"332701","name":"Wangkelang"},{"id":"3327012008","districtId":"332701","name":"Kebanggan"},{"id":"3327012009","districtId":"332701","name":"Pepedan"},{"id":"3327012010","districtId":"332701","name":"Gendoang"}]