[{"id":"3517142001","districtId":"351714","name":"Tanggungkramat"},{"id":"3517142002","districtId":"351714","name":"Rejoagung"},{"id":"3517142003","districtId":"351714","name":"Losari"},{"id":"3517142004","districtId":"351714","name":"Ploso"},{"id":"3517142005","districtId":"351714","name":"Jatigedong"},{"id":"3517142006","districtId":"351714","name":"Daditunggal"},{"id":"3517142007","districtId":"351714","name":"Gedongombo"},{"id":"3517142008","districtId":"351714","name":"Jatibanjar"},{"id":"3517142009","districtId":"351714","name":"Pagertanjung"},{"id":"3517142010","districtId":"351714","name":"Pandanblole"},{"id":"3517142011","districtId":"351714","name":"Kedungdowo"},{"id":"3517142012","districtId":"351714","name":"Kebonagung"},{"id":"3517142013","districtId":"351714","name":"Bawangan"}]