[{"id":"3525092001","districtId":"352509","name":"Sukorejo"},{"id":"3525092002","districtId":"352509","name":"Gedangan"},{"id":"3525092003","districtId":"352509","name":"Wadeng"},{"id":"3525092004","districtId":"352509","name":"Lasem"},{"id":"3525092005","districtId":"352509","name":"Kertosono"},{"id":"3525092006","districtId":"352509","name":"Sambipondok"},{"id":"3525092007","districtId":"352509","name":"Raci Kulon"},{"id":"3525092008","districtId":"352509","name":"Golokan"},{"id":"3525092009","districtId":"352509","name":"Raci Tengah"},{"id":"3525092010","districtId":"352509","name":"Purwodadi"},{"id":"3525092011","districtId":"352509","name":"Sidomulyo"},{"id":"3525092012","districtId":"352509","name":"Srowo"},{"id":"3525092013","districtId":"352509","name":"Kauman"},{"id":"3525092014","districtId":"352509","name":"Bunderan"},{"id":"3525092015","districtId":"352509","name":"Asempapak"},{"id":"3525092016","districtId":"352509","name":"Mriyunan"},{"id":"3525092017","districtId":"352509","name":"Mojoasem"},{"id":"3525092018","districtId":"352509","name":"Sedagaran"},{"id":"3525092019","districtId":"352509","name":"Ngawen"},{"id":"3525092020","districtId":"352509","name":"Pengulu"},{"id":"3525092021","districtId":"352509","name":"Randuboto"}]