[{"id":"3603031001","districtId":"360303","name":"Tigaraksa"},{"id":"3603031007","districtId":"360303","name":"Kadu Agung"},{"id":"3603032002","districtId":"360303","name":"Pasir Bolang"},{"id":"3603032003","districtId":"360303","name":"Matagara"},{"id":"3603032004","districtId":"360303","name":"Pasir Nangka"},{"id":"3603032005","districtId":"360303","name":"Pete"},{"id":"3603032006","districtId":"360303","name":"Tegalsari"},{"id":"3603032008","districtId":"360303","name":"Pematang"},{"id":"3603032009","districtId":"360303","name":"Cisereh"},{"id":"3603032010","districtId":"360303","name":"Margasari"},{"id":"3603032011","districtId":"360303","name":"Cileles"},{"id":"3603032012","districtId":"360303","name":"Sodong"},{"id":"3603032013","districtId":"360303","name":"Tapos"},{"id":"3603032014","districtId":"360303","name":"Bantar Panjang"}]