[{"id":"5102102001","districtId":"510210","name":"Belimbing"},{"id":"5102102002","districtId":"510210","name":"Sanda"},{"id":"5102102003","districtId":"510210","name":"Batungsel"},{"id":"5102102004","districtId":"510210","name":"Kebon Padangan"},{"id":"5102102005","districtId":"510210","name":"Munduktemu"},{"id":"5102102006","districtId":"510210","name":"Pujungan"},{"id":"5102102007","districtId":"510210","name":"Pupuan"},{"id":"5102102008","districtId":"510210","name":"Bantiran"},{"id":"5102102009","districtId":"510210","name":"Padangan"},{"id":"5102102010","districtId":"510210","name":"Jelijih Punggang"},{"id":"5102102011","districtId":"510210","name":"Belatungan"},{"id":"5102102012","districtId":"510210","name":"Pajahan"},{"id":"5102102013","districtId":"510210","name":"Karyasari"},{"id":"5102102014","districtId":"510210","name":"Sai"}]