[{"id":"6207102001","districtId":"620710","name":"Tumbang Magin"},{"id":"6207102002","districtId":"620710","name":"Tumbang Setoli"},{"id":"6207102003","districtId":"620710","name":"Tumbang Hentas"},{"id":"6207102004","districtId":"620710","name":"Tumbang Langkai"},{"id":"6207102005","districtId":"620710","name":"Tumbang Salau"},{"id":"6207102006","districtId":"620710","name":"Tumbang Gugup"},{"id":"6207102007","districtId":"620710","name":"Rangkang Munduk"},{"id":"6207102008","districtId":"620710","name":"Tanjung Tukal"},{"id":"6207102009","districtId":"620710","name":"Rantau Betung"}]