[{"id":"6402172001","districtId":"640217","name":"Sebuntal"},{"id":"6402172002","districtId":"640217","name":"Santan Ulu"},{"id":"6402172003","districtId":"640217","name":"Santan Tengah"},{"id":"6402172004","districtId":"640217","name":"Santan Ilir"},{"id":"6402172005","districtId":"640217","name":"Kersik"},{"id":"6402172006","districtId":"640217","name":"Bunga Putih"},{"id":"6402172007","districtId":"640217","name":"Makarti"},{"id":"6402172008","districtId":"640217","name":"Prangat Selatan"},{"id":"6402172009","districtId":"640217","name":"Prangat Baru"},{"id":"6402172010","districtId":"640217","name":"Semangko"},{"id":"6402172011","districtId":"640217","name":"Sambera Baru"}]