[{"id":"7101142001","districtId":"710114","name":"Bombanon"},{"id":"7101142002","districtId":"710114","name":"Abak"},{"id":"7101142003","districtId":"710114","name":"Tapa Aog"},{"id":"7101142004","districtId":"710114","name":"Mopusi"},{"id":"7101142005","districtId":"710114","name":"Matali Baru"},{"id":"7101142006","districtId":"710114","name":"Bakan"},{"id":"7101142007","districtId":"710114","name":"Tanoyan Selatan"},{"id":"7101142008","districtId":"710114","name":"Tungoi I"},{"id":"7101142009","districtId":"710114","name":"Lolayan"},{"id":"7101142010","districtId":"710114","name":"Mopait"},{"id":"7101142017","districtId":"710114","name":"Kopandakan II"},{"id":"7101142019","districtId":"710114","name":"Tanoyan Utara"},{"id":"7101142020","districtId":"710114","name":"Tungoi II"},{"id":"7101142021","districtId":"710114","name":"Mengkang"}]