[{"id":"7201011006","districtId":"720101","name":"Bugis"},{"id":"7201011007","districtId":"720101","name":"Balantang"},{"id":"7201011008","districtId":"720101","name":"Batui"},{"id":"7201011009","districtId":"720101","name":"Tolando"},{"id":"7201011010","districtId":"720101","name":"Lamo"},{"id":"7201011017","districtId":"720101","name":"Sisipan"},{"id":"7201011023","districtId":"720101","name":"Bakung"},{"id":"7201012002","districtId":"720101","name":"Nonong"},{"id":"7201012003","districtId":"720101","name":"Kayowa"},{"id":"7201012005","districtId":"720101","name":"Ondo-Ondolu"},{"id":"7201012011","districtId":"720101","name":"Honbola"},{"id":"7201012012","districtId":"720101","name":"Uso"},{"id":"7201012016","districtId":"720101","name":"Ondo-Ondolu I"}]