[{"id":"7305061004","districtId":"730506","name":"Bontolebang"},{"id":"7305062001","districtId":"730506","name":"Pakkabba"},{"id":"7305062002","districtId":"730506","name":"Bontolanra"},{"id":"7305062003","districtId":"730506","name":"Aeng Batu Batu"},{"id":"7305062005","districtId":"730506","name":"Tamalate"},{"id":"7305062006","districtId":"730506","name":"Tamasaju"},{"id":"7305062007","districtId":"730506","name":"Bontosunggu"},{"id":"7305062010","districtId":"730506","name":"Aeng Towa"},{"id":"7305062011","districtId":"730506","name":"Bontokaddopepe"},{"id":"7305062012","districtId":"730506","name":"Sampulungan"},{"id":"7305062013","districtId":"730506","name":"Maccini Sombala"},{"id":"7305062014","districtId":"730506","name":"Sawakung Beba"},{"id":"7305062015","districtId":"730506","name":"Biring Kassi"},{"id":"7305062016","districtId":"730506","name":"Kaballokang Pakkabba"}]