[{"id":"7317182001","districtId":"731718","name":"Pompengan"},{"id":"7317182002","districtId":"731718","name":"Bulolondong"},{"id":"7317182003","districtId":"731718","name":"Pompengan pantai"},{"id":"7317182004","districtId":"731718","name":"Seriti"},{"id":"7317182005","districtId":"731718","name":"Salupao"},{"id":"7317182006","districtId":"731718","name":"To'lemo"},{"id":"7317182007","districtId":"731718","name":"Pelalan"},{"id":"7317182008","districtId":"731718","name":"Pompengan Tengah"},{"id":"7317182009","districtId":"731718","name":"Pompengan Utara"}]