[{"id":"7405132001","districtId":"740513","name":"Lamara"},{"id":"7405132002","districtId":"740513","name":"Puuosu"},{"id":"7405132003","districtId":"740513","name":"Benua Utama"},{"id":"7405132004","districtId":"740513","name":"Horodopi"},{"id":"7405132005","districtId":"740513","name":"Benua"},{"id":"7405132006","districtId":"740513","name":"Palowewu"},{"id":"7405132007","districtId":"740513","name":"Punggawukawu"},{"id":"7405132008","districtId":"740513","name":"Uelawa"},{"id":"7405132009","districtId":"740513","name":"Tetehaka"},{"id":"7405132010","districtId":"740513","name":"Awalo"},{"id":"7405132011","districtId":"740513","name":"Kosambi"},{"id":"7405132012","districtId":"740513","name":"Puuwehuko"}]