[{"id":"8201032012","districtId":"820103","name":"Togola Wayoli"},{"id":"8201032013","districtId":"820103","name":"Togola Sangir"},{"id":"8201032014","districtId":"820103","name":"Tahafo"},{"id":"8201032015","districtId":"820103","name":"Tongute Ternate"},{"id":"8201032016","districtId":"820103","name":"Akesibu"},{"id":"8201032017","districtId":"820103","name":"Maritango"},{"id":"8201032018","districtId":"820103","name":"Kie Ici"},{"id":"8201032019","districtId":"820103","name":"Tongute Goin"},{"id":"8201032020","districtId":"820103","name":"Tungute Sungi"},{"id":"8201032021","districtId":"820103","name":"Gam Ici"},{"id":"8201032022","districtId":"820103","name":"Tobaol"},{"id":"8201032023","districtId":"820103","name":"Gamlamo"},{"id":"8201032037","districtId":"820103","name":"Naga"},{"id":"8201032040","districtId":"820103","name":"Soana Masungi"},{"id":"8201032041","districtId":"820103","name":"Tongute Ternate Selatan"},{"id":"8201032042","districtId":"820103","name":"Ake Boso"},{"id":"8201032043","districtId":"820103","name":"Kampung Baru"}]