[{"id":"9106102001","districtId":"910610","name":"Pai"},{"id":"9106102002","districtId":"910610","name":"Auki"},{"id":"9106102003","districtId":"910610","name":"Wundi"},{"id":"9106102004","districtId":"910610","name":"Nusi Babaruk"},{"id":"9106102005","districtId":"910610","name":"Nusi"},{"id":"9106102014","districtId":"910610","name":"Inbeyomi"},{"id":"9106102015","districtId":"910610","name":"Sorina"},{"id":"9106102016","districtId":"910610","name":"Sandidori"},{"id":"9106102020","districtId":"910610","name":"Paidori"},{"id":"9106102021","districtId":"910610","name":"Kanai"},{"id":"9106102022","districtId":"910610","name":"Sokani"}]