[{"id":"9404122001","districtId":"940412","name":"Kapiraya"},{"id":"9404122002","districtId":"940412","name":"Uta"},{"id":"9404122003","districtId":"940412","name":"Mupuruka"},{"id":"9404122004","districtId":"940412","name":"Wumuka"},{"id":"9404122005","districtId":"940412","name":"Akar"},{"id":"9404122006","districtId":"940412","name":"Mapar"},{"id":"9404122007","districtId":"940412","name":"Kipia"},{"id":"9404122008","districtId":"940412","name":"Pronggo"},{"id":"9404122009","districtId":"940412","name":"Wakia"}]