[{"id":"9501112001","districtId":"950111","name":"Yalengga"},{"id":"9501112002","districtId":"950111","name":"Taganik"},{"id":"9501112003","districtId":"950111","name":"Wananuk"},{"id":"9501112004","districtId":"950111","name":"Pilimo"},{"id":"9501112005","districtId":"950111","name":"Tumun"},{"id":"9501112006","districtId":"950111","name":"Akorek"},{"id":"9501112007","districtId":"950111","name":"Manili"},{"id":"9501112008","districtId":"950111","name":"Aipakma"},{"id":"9501112009","districtId":"950111","name":"Wugurima"},{"id":"9501112010","districtId":"950111","name":"Bitti"},{"id":"9501112011","districtId":"950111","name":"Wamanuk Dua"}]