[{"id":"9604082001","districtId":"960408","name":"Mega"},{"id":"9604082002","districtId":"960408","name":"Selewok"},{"id":"9604082003","districtId":"960408","name":"Malaworsai"},{"id":"9604082004","districtId":"960408","name":"Kwade"},{"id":"9604082005","districtId":"960408","name":"Bonem"},{"id":"9604082006","districtId":"960408","name":"Warafor"},{"id":"9604082007","districtId":"960408","name":"Warmasi"},{"id":"9604082008","districtId":"960408","name":"Warmanen"},{"id":"9604082009","districtId":"960408","name":"Namuas"}]