[{"id":"210401","regencyId":"2104","name":"Singkep"},{"id":"210402","regencyId":"2104","name":"Lingga"},{"id":"210403","regencyId":"2104","name":"Senayang"},{"id":"210404","regencyId":"2104","name":"Singkep Barat"},{"id":"210405","regencyId":"2104","name":"Lingga Utara"},{"id":"210406","regencyId":"2104","name":"Singkep Pesisir"},{"id":"210407","regencyId":"2104","name":"Lingga Timur"},{"id":"210408","regencyId":"2104","name":"Selayar"},{"id":"210409","regencyId":"2104","name":"Singkep Selatan"},{"id":"210410","regencyId":"2104","name":"Kepulauan Posek"},{"id":"210411","regencyId":"2104","name":"Katang Bidare"},{"id":"210412","regencyId":"2104","name":"Temiang Pesisir"},{"id":"210413","regencyId":"2104","name":"Bakung Serumpun"}]