[{"id":"740101","regencyId":"7401","name":"Wundulako"},{"id":"740104","regencyId":"7401","name":"Kolaka"},{"id":"740107","regencyId":"7401","name":"Pomalaa"},{"id":"740108","regencyId":"7401","name":"Watubangga"},{"id":"740110","regencyId":"7401","name":"Wolo"},{"id":"740112","regencyId":"7401","name":"Baula"},{"id":"740114","regencyId":"7401","name":"Latambaga"},{"id":"740118","regencyId":"7401","name":"Tanggetada"},{"id":"740120","regencyId":"7401","name":"Samaturu"},{"id":"740124","regencyId":"7401","name":"Toari"},{"id":"740125","regencyId":"7401","name":"Polinggona"},{"id":"740127","regencyId":"7401","name":"Iwoimendaa"}]